{"definitions":{"InputSet":{"required":["EligiblePromotions"],"type":"object","properties":{"EligiblePromotions":{"$ref":"#/definitions/tPromotionList"}},"x-dmn-type":"DMNType{ https://telenor.se/promotion-compatibility : InputSet }","x-dmn-descriptions":{}},"OutputSet":{"type":"object","properties":{"CompatibilityResult":{"x-dmn-type":"FEEL:Any"},"EligiblePromotions":{"$ref":"#/definitions/tPromotionList"}},"x-dmn-type":"DMNType{ https://telenor.se/promotion-compatibility : OutputSet }","x-dmn-descriptions":{}},"tPromotion":{"type":"object","properties":{"promotionId":{"type":"string","x-dmn-type":"FEEL:string"},"promotionName":{"type":"string","x-dmn-type":"FEEL:string"},"promotionBaseType":{"type":"string","x-dmn-type":"FEEL:string"},"discountCategory":{"type":"string","x-dmn-type":"FEEL:string"}},"x-dmn-type":"DMNType{ https://telenor.se/promotion-compatibility : tPromotion }"},"tPromotionList":{"type":"array","items":{"$ref":"#/definitions/tPromotion"},"x-dmn-type":"DMNType{ https://telenor.se/promotion-compatibility : tPromotionList }"}}}